LICENSE
MANIFEST.in
README.md
pyproject.toml
setup.cfg
setup.py
reqs/app.in
reqs/app.txt
reqs/dev.in
reqs/dev.txt
src/greenberry/__init__.py
src/greenberry/debug_cp.py
src/greenberry/gb.py
src/greenberry/gb_ide.py
src/greenberry/gb_main.py
src/greenberry/gb_repl.py
src/greenberry/greenberry_lex_test.py
src/greenberry/main.gb
src/greenberry/math.py
src/greenberry/symbols.py
src/greenberry/test.gb
src/greenberry/theory_notes_simple.py
src/greenberry/utils.py
src/greenberry/x.txt
src/greenberry/y.txt
src/greenberry.egg-info/PKG-INFO
src/greenberry.egg-info/SOURCES.txt
src/greenberry.egg-info/dependency_links.txt
src/greenberry.egg-info/entry_points.txt
src/greenberry.egg-info/requires.txt
src/greenberry.egg-info/top_level.txt
src/greenberry/gb_utils/__init__.py
src/greenberry/gb_utils/greenberry_lex.py
src/greenberry/gb_utils/greenberry_parse.py
src/greenberry/gb_utils/greenberry_plot.py
src/greenberry/gb_utils/greenberry_print.py
src/greenberry/gb_utils/greenberry_search.py
src/greenberry/gb_utils/greenberry_var_type.py
src/greenberry/gbsymbols/__init__.py
src/greenberry/gbsymbols/symbols.py
src/greenberry/gbtest/__init__.py
src/greenberry/gbtest/lang_test.py
src/greenberry/gbtest/utils_test.py
src/greenberry/gbtools/__init__.py
src/greenberry/gbtools/lexer.py
src/greenberry/gbtools/parser.py