Metadata-Version: 2.1
Name: greenberry
Version: 0.9.0
Summary: lang compiler-theory interpreter
Home-page: https://github.com/Abdur-RahmaanJ/greenBerry
Author: Abdur-Rahmaan Janhangeer & contributors
Author-email: arj.python@gmail.com
Project-URL: Bug Reports, https://github.com/Abdur-RahmaanJ/greenBerry/issues
Project-URL: Source, https://github.com/Abdur-RahmaanJ/greenBerry/
Keywords: flask pos management shop ecommerce cms erp
Classifier: Development Status :: 4 - Beta
Classifier: Intended Audience :: Developers
Classifier: License :: OSI Approved :: MIT License
Classifier: Programming Language :: Python :: 3.6
Classifier: Programming Language :: Python :: 3.7
Classifier: Programming Language :: Python :: 3.8
Classifier: Programming Language :: Python :: 3.9
Classifier: Programming Language :: Python :: 3.10
Requires-Python: >=3.4
Provides-Extra: dev
License-File: LICENSE
